subtitle_increment/__init__.py
subtitle_increment/__main__.py
subtitle_increment/incrementer.py
subtitle_increment-1.0.1.dist-info/LICENSE
subtitle_increment-1.0.1.dist-info/METADATA
subtitle_increment-1.0.1.dist-info/WHEEL
subtitle_increment-1.0.1.dist-info/top_level.txt
subtitle_increment-1.0.1.dist-info/RECORD
