Metadata-Version: 2.1
Name: subtitle-increment
Version: 1.0.1
Summary: Increments srt files forwards or backwards in time
Home-page: https://github.com/Michaeljurado24/subtitle-increment.git
Author: Michael Jurado
Author-email: michaeljurado42@gmail.com
License: CC0 1.0 Universal
Platform: UNKNOWN
Classifier: Programming Language :: Python :: 3
Classifier: Programming Language :: Python :: 3.7
License-File: LICENSE
